intake_dataframe_catalog/__init__.py
intake_dataframe_catalog/_display.py
intake_dataframe_catalog/_search.py
intake_dataframe_catalog/_utils.py
intake_dataframe_catalog/_version.py
intake_dataframe_catalog/core.py
intake_dataframe_catalog-0.5.1.dist-info/licenses/LICENSE
intake_dataframe_catalog-0.5.1.dist-info/METADATA
intake_dataframe_catalog-0.5.1.dist-info/WHEEL
intake_dataframe_catalog-0.5.1.dist-info/entry_points.txt
intake_dataframe_catalog-0.5.1.dist-info/top_level.txt
intake_dataframe_catalog-0.5.1.dist-info/RECORD
