Metadata-Version: 2.4
Name: intake_dataframe_catalog
Version: 0.5.1
Summary: An intake driver for a searchable table of intake sources and associated metadata
Author: ACCESS-NRI
License: Apache-2.0
Classifier: Development Status :: 4 - Beta
Classifier: Programming Language :: Python :: 3
Classifier: License :: OSI Approved :: Apache Software License
Classifier: Operating System :: OS Independent
Requires-Python: >=3.10
License-File: LICENSE
Requires-Dist: intake>=0.7.0
Requires-Dist: itables
Requires-Dist: pandas
Requires-Dist: polars<1.33,>=1.12
Provides-Extra: test
Requires-Dist: pytest; extra == "test"
Requires-Dist: pytest-cov; extra == "test"
Requires-Dist: tox; extra == "test"
Dynamic: license-file
